vl8.py
vl8-0.2.0.dist-info/LICENSE
vl8-0.2.0.dist-info/METADATA
vl8-0.2.0.dist-info/WHEEL
vl8-0.2.0.dist-info/top_level.txt
vl8-0.2.0.dist-info/RECORD
